cloudmodel.libs/libquadmath-96973f99.so.0.0.0
cloudmodel.libs/libgfortran-040039e1.so.5.0.0
cloudmodel-1.0.1.dist-info/METADATA
cloudmodel-1.0.1.dist-info/RECORD
cloudmodel-1.0.1.dist-info/WHEEL
cloudmodel-1.0.1.dist-info/entry_points.txt
cloudmodel/z_profile.py
cloudmodel/constants.py
cloudmodel/cloud_read.py
cloudmodel/__init__.py
cloudmodel/interface/__init__.py
cloudmodel/interface/cloud_compiled.cpython-310-x86_64-linux-gnu.so
