Metadata-Version: 2.1
Name: cloudmodel
Version: 1.0.1
Summary: A simple, parameterized cloud model
Keywords: simulator,cloud,fortran,python,modeling
Author-Email: "Diego E. Oleiarz" <diego.oleiarz@mi.unc.edu.ar>
License: The MIT License
Classifier: Development Status :: 4 - Beta
Classifier: Intended Audience :: Education
Classifier: Intended Audience :: Science/Research
Classifier: License :: OSI Approved :: MIT License
Classifier: Programming Language :: Python :: 3
Classifier: Programming Language :: Python :: 3.10
Classifier: Programming Language :: Python :: 3.11
Classifier: Programming Language :: Python :: 3.12
Classifier: Operating System :: OS Independent
Classifier: Topic :: Scientific/Engineering
Project-URL: Homepage, https://github.com/Diegoolei/Fortran77-Cloud-Model
Project-URL: Documentation, https://diegoolei.github.io/Fortran77-Cloud-Model/
Requires-Python: <3.13,>=3.10
Requires-Dist: numpy
Requires-Dist: pandas
Requires-Dist: scipy
Requires-Dist: fpm
Requires-Dist: matplotlib
Requires-Dist: meson
Requires-Dist: ninja
